Workbook

Sheet Comerciales
A1: ID_Comercial | B1: Nombre | C1: Email | D1: Teléfono | E1: Zona
A2: V001 | B2: Luis García | C2: Luilli78@gmail.com | D2: 610385264 | E2: A Coruña
A3: V002 | B3: Juan Pérez | C3: JuanPerez80@gmail.com | D3: 675254512 | E3: Lugo
A4: V003 | B4: Javier Prieto | C4: JotaPrieto71@hotmail.com | D4: 666235698 | E4: Ourense
A5: V004 | B5: Yolanda Gómez | C5: YoliGondar97@gmail.com | D5: 600251478 | E5: Pontevedra

Sheet Productos
A1: ID_Producto | B1: Nombre_Producto | C1: Categoría | D1: Precio_Venta | E1: Precio_compra | F1: ID_Proveedor
A2: P001 | B2: Plátano | C2: Frutas frescas | D2: 2.3 | E2: 1.058 | F2: Prov009
A3: P002 | B3: Uva | C3: Frutas frescas | D3: 2.9 | E3: 1.131 | F3: Prov005
A4: P003 | B4: Melón | C4: Frutas frescas | D4: 1.35 | E4: 0.4725 | F4: Prov001
A5: P004 | B5: Sandía | C5: Frutas frescas | D5: 1.2 | E5: 0.456 | F5: Prov001
A6: P005 | B6: Fresa | C6: Frutas frescas | D6: 3.2 | E6: 1.152 | F6: Prov008
A7: P006 | B7: Kiwi | C7: Frutas frescas | D7: 2.5 | E7: 0.9 | F7: Prov008
A8: P007 | B8: Granada | C8: Frutas frescas | D8: 2.8 | E8: 1.26 | F8: Prov008
A9: P008 | B9: Lechuga | C9: Verduras y hortalizas | D9: 1.13 | E9: 0.4407 | F9: Prov002
A10: P009 | B10: Tomate | C10: Verduras y hortalizas | D10: 2.22 | E10: 0.9546 | F10: Prov001
A11: P010 | B11: Pimiento | C11: Verduras y hortalizas | D11: 2.4 | E11: 1.008 | F11: Prov001
A12: P011 | B12: Cebolla | C12: Verduras y hortalizas | D12: 1.66 | E12: 0.6806 | F12: Prov002
A13: P012 | B13: Calabacín | C13: Verduras y hortalizas | D13: 1.8 | E13: 0.828 | F13: Prov001
... A64: P063 | B64: Boletus edulis | C64: Setas y hongos | D64: 9.8 | E64: 4.606 | F64: Prov006

Sheet Clientes
A1: ID_Cliente | B1: Nombre_Cliente | C1: NIF_CIF | D1: Dirección | E1: Código_Postal | F1: Ciudad | G1: Provincia | H1: País | I1: Teléfono | J1: Email
A2: C001 | B2: Alejandro García | C2: 12345678A | D2: Rúa Arcebispo Lago 22 | E2: 27400 | F2: Monforte | G2: Lugo | H2: España | I2: 612345678 | J2: AleGarc@yahoo.com
A3: C002 | B3: María Fernández | C3: 67890123F | D3: Calle Mayor 7 | E3: 15401 | F3: Ferrol | G3: A Coruña | H3: España | I3: 622345679 | J3: MarFern@yahoo.com
A4: C003 | B4: Javier Rodríguez | C4: 13579246L | D4: Avenida del Atlántico 74 | E4: 27880 | F4: Burela | G4: Lugo | H4: España | I4: 632345680 | J4: JavRodr@hotmail.com
A5: C004 | B5: Carmen López | C5: 68035791R | D5: Plaza de la Constitución 76 | E5: 15401 | F5: Ferrol | G5: A Coruña | H5: España | I5: 642345681 | J5: CarLópe@outlook.es
A6: C005 | B6: Luis Martínez | C6: 11112222X | D6: Paseo de los Laureles 24 | E6: 32600 | F6: Verín | G6: Ourense | H6: España | I6: 652345682 | J6: LuiMart@gmail.com
A7: C006 | B7: Ana Sánchez | C7: 66667777C | D7: Travesía del Mirador 83 | E7: 15570 | F7: Narón | G7: A Coruña | H7: España | I7: 662345683 | J7: AnaSánc@outlook.es
A8: C007 | B8: Pablo González | C8: 11223344H | D8: Calle del Sol 39 | E8: 32600 | F8: Verín | G8: Ourense | H8: España | I8: 672345684 | J8: PabGonz@gmail.com
A9: C008 | B9: Laura Pérez | C9: 66778899N | D9: Avenida de Canarias 40 | E9: 27800 | F9: Vilalba | G9: Lugo | H9: España | I9: 682345685 | J9: LauPére@yahoo.com
A10: C009 | B10: Diego Romero | C10: 12131415T | D10: Plaza del Mar 125 | E10: 36001 | F10: Pontevedra | G10: Pontevedra | H10: España | I10: 692345686 | J10: DieRome@outlook.com
A11: C010 | B11: Isabel Torres | C11: 17181920Z | D11: Camino Real 116 | E11: 15401 | F11: Ferrol | G11: A Coruña | H11: España | I11: 602345687 | J11: IsaTorr@outlook.es
A12: C011 | B12: Sergio Ruiz | C12: 22232425E | D12: Calle de los Pinos 20 | E12: 36600 | F12: Vilagarcía | G12: Pontevedra | H12: España | I12: 612345688 | J12: SerRuiz@gmail.com
A13: C012 | B13: Marta Morales | C13: 27282930K | D13: Avenida del Teide 120 | E13: 32500 | F13: O Carballiño | G13: Ourense | H13: España | I13: 622345689 | J13: MarMora@hotmail.com
... A101: C100 | B101: Julia Espinosa | C101: 71727374H | D101: Camino de los Helechos 62 | E101: 27880 | F101: Burela | G101: Lugo | H101: España | I101: 602345677 | J101: JulEspi@outlook.es

Sheet Facturas_ventas
A1: ID_Factura | B1: ID_Linea | C1: ID_Producto | D1: Descripción | E1: Cantidad | F1: Precio_Unitario | G1: Importe_Linea | H1: ID_Comercial | I1: ID_Cliente | J1: Fecha_Emisión | K1: Fecha_Vencimiento | L1: Forma_Pago
A2: FV0001 | B2: L001 | C2: P003 | D2: Melón | E2: 10 | F2: 1.35 | G2: 13.5 | H2: V001 | I2: C080 | J2: 45292 | K2: 45322 | L2: Bizum
A3: FV0001 | B3: L002 | C3: P035 | D3: Chirimoya | E3: 6 | F3: 3.2 | G3: 19.2 | H3: V001 | I3: C080 | J3: 45292 | K3: 45322 | L3: Bizum
A4: FV0002 | B4: L001 | C4: P062 | D4: Níscalo | E4: 14 | F4: 6.5 | G4: 91 | H4: V001 | I4: C039 | J4: 45292 | K4: 45322 | L4: Efectivo
A5: FV0003 | B5: L001 | C5: P041 | D5: Cereza | E5: 10 | F5: 5.5 | G5: 55 | H5: V002 | I5: C053 | J5: 45292 | K5: 45322 | L5: Transferencia
A6: FV0003 | B6: L002 | C6: P007 | D6: Granada | E6: 10 | F6: 2.8 | G6: 28 | H6: V002 | I6: C053 | J6: 45292 | K6: 45322 | L6: Transferencia
A7: FV0003 | B7: L003 | C7: P024 | D7: Guisante | E7: 8 | F7: 2.2 | G7: 17.6 | H7: V002 | I7: C053 | J7: 45292 | K7: 45322 | L7: Transferencia
A8: FV0004 | B8: L001 | C8: P024 | D8: Guisante | E8: 20 | F8: 2.2 | G8: 44 | H8: V004 | I8: C015 | J8: 45292 | K8: 45322 | L8: Efectivo
A9: FV0004 | B9: L002 | C9: P053 | D9: Naranja sanguina | E9: 14 | F9: 2.5 | G9: 35 | H9: V004 | I9: C015 | J9: 45292 | K9: 45322 | L9: Efectivo
A10: FV0005 | B10: L001 | C10: P012 | D10: Calabacín | E10: 16 | F10: 1.8 | G10: 28.8 | H10: V003 | I10: C057 | J10: 45292 | K10: 45322 | L10: Bizum
A11: FV0006 | B11: L001 | C11: P008 | D11: Lechuga | E11: 9 | F11: 1.13 | G11: 10.17 | H11: V001 | I11: C010 | J11: 45292 | K11: 45322 | L11: Efectivo
A12: FV0006 | B12: L002 | C12: P009 | D12: Tomate | E12: 16 | F12: 2.22 | G12: 35.52 | H12: V001 | I12: C010 | J12: 45292 | K12: 45322 | L12: Efectivo
A13: FV0006 | B13: L003 | C13: P032 | D13: Guayaba | E13: 10 | F13: 3.8 | G13: 38 | H13: V001 | I13: C010 | J13: 45292 | K13: 45322 | L13: Efectivo
... A6806: FV3500 | B6806: L001 | C6806: P055 | D6806: Boniato | E6806: 11 | F6806: 2.1 | G6806: 23.1 | H6806: V003 | I6806: C007 | J6806: 45657 | K6806: 45687 | L6806: Bizum

Sheet Proveedores
A1: ID_Proveedor | B1: Nombre_Proveedor | C1: NIF_CIF | D1: Dirección | E1: Código Postal | F1: Ciudad | G1: Provincia | H1: País | I1: Teléfono | J1: Email
A2: Prov001 | B2: Frutas Martínez S.L. | C2: 12345678A | D2: Calle del Olivo, 24 | E2: 30720 | F2: San Javier | G2: Murcia | H2: España | I2: 634789201 | J2: frutasmartinez@gmail.com
A3: Prov002 | B3: Cooperativa Agraria del Sur | C3: 87654321B | D3: Avenida de la Vega, 15 | E3: 4700 | F3: El Ejido | G3: Almería | H3: España | I3: 698432157 | J3: cooperativaagrariasur@gmail.com
A4: Prov003 | B4: Hortalizas González | C4: 45678912C | D4: Camino de los Invernaderos, 12 | E4: 30730 | F4: San Pedro del Pinatar | G4: Murcia | H4: España | I4: 672198304 | J4: hortalizasgonzalez@gmail.com
A5: Prov004 | B5: Agrovalle Levante S.Coop. | C5: 34127895D | D5: Carretera Nacional 332, km 54 | E5: 3350 | F5: Callosa de Segura | G5: Alicante | H5: España | I5: 639725841 | J5: agrovallelevante@gmail.com
A6: Prov005 | B6: Verduras López e Hijos | C6: 59438217E | D6: Calle del Mercado, 8 | E6: 46200 | F6: Paiporta | G6: Valencia | H6: España | I6: 661394728 | J6: verduraslopez@gmail.com
A7: Prov006 | B7: Huerta Segoviana S.L. | C7: 21789453F | D7: Camino del Prado, 22 | E7: 40195 | F7: Hontoria | G7: Segovia | H7: España | I7: 679843520 | J7: huertasegoviana@gmail.com
A8: Prov007 | B8: Campos de Navarra Coop. | C8: 32897541G | D8: Calle del Ebro, 17 | E8: 31500 | F8: Tudela | G8: Navarra | H8: España | I8: 687910234 | J8: camposdenavarra@gmail.com
A9: Prov008 | B9: Frutas y Verduras Pérez | C9: 75943182H | D9: Avenida del Campo, 5 | E9: 14920 | F9: Aguilar de la Frontera | G9: Córdoba | H9: España | I9: 693285471 | J9: frutasyverdurasperez@gmail.com
A10: Prov009 | B10: La Huerta Manchega S.L. | C10: 68521437J | D10: Calle Real, 10 | E10: 13700 | F10: Tomelloso | G10: Ciudad Real | H10: España | I10: 676432195 | J10: lahuertamanchega@gmail.com
A11: Prov010 | B11: Agrícola del Ebro S.A. | C11: 49837216K | D11: Camino de la Ribera, 3 | E11: 50600 | F11: Ejea de los Caballeros | G11: Zaragoza | H11: España | I11: 690718342 | J11: agricoladelebro@gmail.com

Sheet Facturas_compras
A1: ID_Factura | B1: ID_Linea | C1: ID_Producto | D1: Descripción | E1: Cantidad | F1: Precio_Unitario | G1: Importe_Linea | H1: ID_Proveedor | I1: Fecha_Emisión | J1: ID_Comercial
A2: FC0001 | B2: L001 | C2: P003 | D2: Melón | E2: 10 | F2: =VLOOKUP(D2,Productos!$B:$E,4,FALSE) -> 0.4725 | G2: =E2*F2 -> 4.725 | H2: =VLOOKUP(C2,Productos!$A:$F,6,FALSE) -> Prov001 | I2: 45292 | J2: V001
A3: FC0001 | B3: L002 | C3: P035 | D3: Chirimoya | E3: 6 | F3: =VLOOKUP(D3,Productos!$B:$E,4,FALSE) -> 1.44 | G3: =E3*F3 -> 8.64 | H3: =VLOOKUP(C3,Productos!$A:$F,6,FALSE) -> Prov010 | I3: 45292 | J3: V001
A4: FC0002 | B4: L001 | C4: P062 | D4: Níscalo | E4: 14 | F4: =VLOOKUP(D4,Productos!$B:$E,4,FALSE) -> 3.185 | G4: =E4*F4 -> 44.59 | H4: =VLOOKUP(C4,Productos!$A:$F,6,FALSE) -> Prov006 | I4: 45292 | J4: V001
A5: FC0003 | B5: L001 | C5: P041 | D5: Cereza | E5: 10 | F5: =VLOOKUP(D5,Productos!$B:$E,4,FALSE) -> 2.42 | G5: =E5*F5 -> 24.2 | H5: =VLOOKUP(C5,Productos!$A:$F,6,FALSE) -> Prov008 | I5: 45292 | J5: V002
A6: FC0003 | B6: L002 | C6: P007 | D6: Granada | E6: 10 | F6: =VLOOKUP(D6,Productos!$B:$E,4,FALSE) -> 1.26 | G6: =E6*F6 -> 12.6 | H6: =VLOOKUP(C6,Productos!$A:$F,6,FALSE) -> Prov008 | I6: 45292 | J6: V002
A7: FC0003 | B7: L003 | C7: P024 | D7: Guisante | E7: 8 | F7: =VLOOKUP(D7,Productos!$B:$E,4,FALSE) -> 1.056 | G7: =E7*F7 -> 8.448 | H7: =VLOOKUP(C7,Productos!$A:$F,6,FALSE) -> Prov007 | I7: 45292 | J7: V002
A8: FC0004 | B8: L001 | C8: P024 | D8: Guisante | E8: 20 | F8: =VLOOKUP(D8,Productos!$B:$E,4,FALSE) -> 1.056 | G8: =E8*F8 -> 21.12 | H8: =VLOOKUP(C8,Productos!$A:$F,6,FALSE) -> Prov007 | I8: 45292 | J8: V004
A9: FC0004 | B9: L002 | C9: P053 | D9: Naranja sanguina | E9: 14 | F9: =VLOOKUP(D9,Productos!$B:$E,4,FALSE) -> 1.175 | G9: =E9*F9 -> 16.45 | H9: =VLOOKUP(C9,Productos!$A:$F,6,FALSE) -> Prov004 | I9: 45292 | J9: V004
A10: FC0005 | B10: L001 | C10: P012 | D10: Calabacín | E10: 16 | F10: =VLOOKUP(D10,Productos!$B:$E,4,FALSE) -> 0.828 | G10: =E10*F10 -> 13.248 | H10: =VLOOKUP(C10,Productos!$A:$F,6,FALSE) -> Prov001 | I10: 45292 | J10: V003
A11: FC0006 | B11: L001 | C11: P008 | D11: Lechuga | E11: 9 | F11: =VLOOKUP(D11,Productos!$B:$E,4,FALSE) -> 0.4407 | G11: =E11*F11 -> 3.9663 | H11: =VLOOKUP(C11,Productos!$A:$F,6,FALSE) -> Prov002 | I11: 45292 | J11: V001
A12: FC0006 | B12: L002 | C12: P009 | D12: Tomate | E12: 16 | F12: =VLOOKUP(D12,Productos!$B:$E,4,FALSE) -> 0.9546 | G12: =E12*F12 -> 15.2736 | H12: =VLOOKUP(C12,Productos!$A:$F,6,FALSE) -> Prov001 | I12: 45292 | J12: V001
A13: FC0006 | B13: L003 | C13: P032 | D13: Guayaba | E13: 10 | F13: =VLOOKUP(D13,Productos!$B:$E,4,FALSE) -> 1.862 | G13: =E13*F13 -> 18.62 | H13: =VLOOKUP(C13,Productos!$A:$F,6,FALSE) -> Prov010 | I13: 45292 | J13: V001
... A6806: FC3500 | B6806: L001 | C6806: P055 | D6806: Boniato | E6806: 11 | F6806: =VLOOKUP(D6806,Productos!$B:$E,4,FALSE) -> 1.029 | G6806: =E6806*F6806 -> 11.319 | H6806: =VLOOKUP(C6806,Productos!$A:$F,6,FALSE) -> Prov003 | I6806: 45657 | J6806: V003
